rpi_flash/__main__.py
rpi_flash/flash.py
rpi_flash-0.1.3.dist-info/entry_points.txt
rpi_flash-0.1.3.dist-info/WHEEL
rpi_flash-0.1.3.dist-info/METADATA
rpi_flash-0.1.3.dist-info/RECORD
