Metadata-Version: 2.1
Name: rpi-flash
Version: 0.1.3
Summary: 
Home-page: https://github.com/jonohill/rpi-flash
Author: Jono Hill
Author-email: jono@hillnz.com
Requires-Python: >=3.8,<4.0
Classifier: Programming Language :: Python :: 3
Classifier: Programming Language :: Python :: 3.8
Classifier: Programming Language :: Python :: 3.9
Requires-Dist: humanize (>=3.9.0,<4.0.0)
Requires-Dist: pydantic (>=1.8.2,<2.0.0)
Requires-Dist: requests (>=2.25.1,<3.0.0)
Requires-Dist: typer (>=0.3.2,<0.4.0)
Project-URL: Repository, https://github.com/jonohill/rpi-flash
